audioscrape/__init__.py
audioscrape/client.py
audioscrape/notifications/__init__.py
audioscrape/notifications/api.py
audioscrape/search/__init__.py
audioscrape/search/api.py
audioscrape_sdk-0.1.0.dist-info/METADATA
audioscrape_sdk-0.1.0.dist-info/WHEEL
audioscrape_sdk-0.1.0.dist-info/top_level.txt
audioscrape_sdk-0.1.0.dist-info/RECORD
