Metadata-Version: 2.4
Name: audioscrape-sdk
Version: 0.1.0
Summary: Official Python SDK for Audioscrape API
Home-page: https://github.com/audioscrape/python-sdk
Author: Audioscrape Team
Author-email: support@audioscrape.com
Classifier: Programming Language :: Python :: 3
Classifier: License :: OSI Approved :: MIT License
Classifier: Operating System :: OS Independent
Requires-Python: >=3.6
Requires-Dist: requests>=2.25.0
Dynamic: author
Dynamic: author-email
Dynamic: classifier
Dynamic: description
Dynamic: description-content-type
Dynamic: home-page
Dynamic: requires-dist
Dynamic: requires-python
Dynamic: summary
